{
  "items": [
    {
      "title": "Машинист экскаватора",
      "department": "Производство",
      "schedule": "Вахта 30/30",
      "salary": "от 450 000 ₸",
      "requirements": [
        { "item": "Опыт работы на карьерных экскаваторах от 3 лет" },
        { "item": "Удостоверение машиниста экскаватора" },
        { "item": "Готовность к вахтовому методу работы" }
      ],
      "active": true
    },
    {
      "title": "Водитель БелАЗ",
      "department": "Производство",
      "schedule": "Вахта 15/15",
      "salary": "от 380 000 ₸",
      "requirements": [
        { "item": "Категория водительского удостоверения E" },
        { "item": "Опыт управления карьерной техникой от 2 лет" },
        { "item": "Прохождение медицинской комиссии" }
      ],
      "active": true
    }
  ]
}